rtnf/__init__.py
rtnf/src/__init__.py
rtnf/src/rtnf.py
rtnf/test/__init__.py
rtnf/test/test_rtnf.py
rtnf-1.0.0.dist-info/METADATA
rtnf-1.0.0.dist-info/WHEEL
rtnf-1.0.0.dist-info/top_level.txt
rtnf-1.0.0.dist-info/RECORD
