Metadata-Version: 2.1
Name: rtnf
Version: 1.0.0
Summary: Royal Thai Navy string format manipulation tools
Home-page: https://github.com/anuwatavis/royal-thai-navy-string-format
Author: anuwataravis
Author-email: anuwat.avis@gmail.com
License: MIT
Keywords: rtnf royal thai navy string format
Classifier: License :: OSI Approved :: MIT License
Classifier: Programming Language :: Python :: 3.10
Classifier: Operating System :: OS Independent
Requires-Python: >=3.8
Provides-Extra: dev
Requires-Dist: twine (>=4.0.2) ; extra == 'dev'
